{
  "recentFiles": [
    {
      "basename": "●首頁",
      "path": "●首頁.md"
    },
    {
      "basename": "2022-10-17_Mon",
      "path": "006-DailyNote/2022-10-17_Mon.md"
    },
    {
      "basename": "Obsidian統整筆記",
      "path": "003-●專案管理/003-Obsidian學習筆記/Obsidian統整筆記.md"
    },
    {
      "basename": "●日常生活待辦事項",
      "path": "004-●日常生活/●日常生活待辦事項.md"
    },
    {
      "basename": "1110717-能量運動指南",
      "path": "004-●日常生活/005-健康知識/1110717-能量運動指南.md"
    },
    {
      "basename": "1110911-Excel VBA學習相關",
      "path": "003-●專案管理/006-Excel學習相關/1110911-Excel VBA學習相關.md"
    },
    {
      "basename": "1110911-Excel快速合併寄送郵件",
      "path": "003-●專案管理/006-Excel學習相關/1110911-Excel快速合併寄送郵件.md"
    },
    {
      "basename": "●投資理財及創業待辦事項",
      "path": "003-●專案管理/005-投資理財相關/●投資理財及創業待辦事項.md"
    },
    {
      "basename": "1110906-Obsidian快捷鍵",
      "path": "003-●專案管理/003-Obsidian學習筆記/1110906-Obsidian快捷鍵.md"
    },
    {
      "basename": "1110721-MAMP教學（在電腦安裝離線版伺服器及WordPress）",
      "path": "003-●專案管理/001-WordPress架設網站/1110721-MAMP教學（在電腦安裝離線版伺服器及WordPress）.md"
    },
    {
      "basename": "●美食",
      "path": "007-旅遊、景點、美食/●美食.md"
    },
    {
      "basename": "●工作待辦事項",
      "path": "005-工作相關/●工作待辦事項.md"
    },
    {
      "basename": "2022-10-16_Sun",
      "path": "006-DailyNote/2022-10-16_Sun.md"
    },
    {
      "basename": "WordPress學習及筆記",
      "path": "003-●專案管理/001-WordPress架設網站/WordPress學習及筆記.md"
    },
    {
      "basename": "1111010-電路板維修（三用電表操作使用）新手教學",
      "path": "004-●日常生活/007-修繕、工具知識/1111010-電路板維修（三用電表操作使用）新手教學.md"
    },
    {
      "basename": "電腦知識",
      "path": "004-●日常生活/003-電腦知識/電腦知識.md"
    },
    {
      "basename": "2022-10-14_Fri",
      "path": "006-DailyNote/2022-10-14_Fri.md"
    },
    {
      "basename": "●日常生活紀錄",
      "path": "004-●日常生活/●日常生活紀錄.md"
    },
    {
      "basename": "Daily Note Template",
      "path": "001-Template/Daily Note Template.md"
    },
    {
      "basename": "★測試各類功能",
      "path": "★測試各類功能.md"
    },
    {
      "basename": "●高中以下人事法規彙整",
      "path": "005-工作相關/001-人事法規/●高中以下人事法規彙整.md"
    },
    {
      "basename": "校長遴選座談會及後續工作",
      "path": "005-工作相關/●已完成/校長遴選座談會及後續工作.md"
    },
    {
      "basename": "!dict",
      "path": "000-index/!dict.md"
    },
    {
      "basename": "2022-10-13_Thu",
      "path": "006-DailyNote/2022-10-13_Thu.md"
    },
    {
      "basename": "2022-10-12_Wed",
      "path": "006-DailyNote/2022-10-12_Wed.md"
    },
    {
      "basename": "1111012-WordPress架站心得",
      "path": "003-●專案管理/001-WordPress架設網站/1111012-WordPress架站心得.md"
    },
    {
      "basename": "●專案管理",
      "path": "●專案管理.md"
    },
    {
      "basename": "Obsidian的任務管理技巧彙總",
      "path": "003-●專案管理/003-Obsidian學習筆記/Obsidian的任務管理技巧彙總.md"
    },
    {
      "basename": "1110731-DataView插件筆記",
      "path": "003-●專案管理/003-Obsidian學習筆記/1110731-DataView插件筆記.md"
    },
    {
      "basename": "2022-09-26_Mon",
      "path": "006-DailyNote/2022-09-26_Mon.md"
    },
    {
      "basename": "2022-10-11_Tue",
      "path": "006-DailyNote/2022-10-11_Tue.md"
    },
    {
      "basename": "WordPress是什麼 ？完整介紹評價＋教學範例（入門指南）",
      "path": "003-●專案管理/001-WordPress架設網站/WordPress是什麼 ？完整介紹評價＋教學範例（入門指南）.md"
    },
    {
      "basename": "2022-10-10_Mon",
      "path": "006-DailyNote/2022-10-10_Mon.md"
    },
    {
      "basename": "2022-10-09_Sun",
      "path": "006-DailyNote/2022-10-09_Sun.md"
    },
    {
      "basename": "2022-10-08_Sat",
      "path": "006-DailyNote/2022-10-08_Sat.md"
    },
    {
      "basename": "2022-10-07_Fri",
      "path": "006-DailyNote/2022-10-07_Fri.md"
    },
    {
      "basename": "2022-10-06_Thu",
      "path": "006-DailyNote/2022-10-06_Thu.md"
    },
    {
      "basename": "2022-10-05_Wed",
      "path": "006-DailyNote/2022-10-05_Wed.md"
    },
    {
      "basename": "1110814-Thinkorswim軟體學習心得",
      "path": "003-●專案管理/005-投資理財相關/1110814-Thinkorswim軟體學習心得.md"
    },
    {
      "basename": "電腦疑難雜症",
      "path": "004-●日常生活/003-電腦知識/電腦疑難雜症.md"
    },
    {
      "basename": "2022-10-04_Tue",
      "path": "006-DailyNote/2022-10-04_Tue.md"
    },
    {
      "basename": "2022-10-03_Mon",
      "path": "006-DailyNote/2022-10-03_Mon.md"
    },
    {
      "basename": "Daily Note Tasks",
      "path": "001-Template/Daily Note Tasks.md"
    },
    {
      "basename": "1110925-老屋翻修估價相關",
      "path": "004-●日常生活/007-修繕、工具知識/1110925-老屋翻修估價相關.md"
    },
    {
      "basename": "2022-10-02_Sun",
      "path": "006-DailyNote/2022-10-02_Sun.md"
    },
    {
      "basename": "2022-09-30_Fri",
      "path": "006-DailyNote/2022-09-30_Fri.md"
    },
    {
      "basename": "2022-09-29_Thu",
      "path": "006-DailyNote/2022-09-29_Thu.md"
    },
    {
      "basename": "2022-09-28_Wed",
      "path": "006-DailyNote/2022-09-28_Wed.md"
    },
    {
      "basename": "2022-09-27_Tue",
      "path": "006-DailyNote/2022-09-27_Tue.md"
    },
    {
      "basename": "2022-09-25_Sun",
      "path": "006-DailyNote/2022-09-25_Sun.md"
    }
  ],
  "omittedPaths": [],
  "maxLength": null
}